axis_registry/__init__.py
axis_registry/agent_registry.py
axis_registry/skill_registry.py
lumpi_axis_registry-0.1.1.dist-info/licenses/LICENSE
lumpi_axis_registry-0.1.1.dist-info/METADATA
lumpi_axis_registry-0.1.1.dist-info/WHEEL
lumpi_axis_registry-0.1.1.dist-info/top_level.txt
lumpi_axis_registry-0.1.1.dist-info/RECORD
