Metadata-Version: 2.4
Name: lumpi-axis-registry
Version: 0.1.1
Summary: AXIS Registry - Agent and skill discovery service
Author-email: Emily Veiga <emily@lumpi.ai>
License: MIT
Project-URL: Homepage, https://github.com/emilyveigaai/axis-registry
Project-URL: Documentation, https://github.com/emilyveigaai/axis-registry#readme
Project-URL: Repository, https://github.com/emilyveigaai/axis-registry
Project-URL: Issues, https://github.com/emilyveigaai/axis-registry/issues
Requires-Python: >=3.10
License-File: LICENSE
Requires-Dist: axis-sdk<1.0.0,>=0.3.0
Requires-Dist: pyyaml>=6.0.0
Provides-Extra: dev
Requires-Dist: pytest>=7.0.0; extra == "dev"
Requires-Dist: pytest-cov>=4.0.0; extra == "dev"
Requires-Dist: black>=23.0.0; extra == "dev"
Requires-Dist: ruff>=0.1.0; extra == "dev"
Requires-Dist: mypy>=1.0.0; extra == "dev"
Dynamic: license-file
